{"cameraMode":{"drawMode":0,"name":"Shaded","section":"Shading Mode"},"sceneLighting":true,"audioPlay":false,"sceneViewState":{"m_AlwaysRefresh":false,"showFog":true,"showSkybox":true,"showFlares":true,"showImageEffects":true,"showParticleSystems":true,"showVisualEffectGraphs":true,"m_FxEnabled":true},"in2DMode":false,"pivot":{"x":-0.39999961853027346,"y":3.2119498252868654,"z":-3.950000286102295},"rotation":{"x":0.3487476706504822,"y":0.23261165618896485,"z":-0.08979365974664688,"w":0.9034424424171448},"size":26.76882553100586,"orthographic":false}